{ "frames": {
   "select_button 0.aseprite": {
    "frame": { "x": 0, "y": 0, "w": 16, "h": 25 },
    "rotated": false,
    "trimmed": false,
    "spriteSourceSize": { "x": 0, "y": 0, "w": 16, "h": 25 },
    "sourceSize": { "w": 16, "h": 25 },
    "duration": 500
   },
   "select_button 1.aseprite": {
    "frame": { "x": 16, "y": 0, "w": 16, "h": 25 },
    "rotated": false,
    "trimmed": false,
    "spriteSourceSize": { "x": 0, "y": 0, "w": 16, "h": 25 },
    "sourceSize": { "w": 16, "h": 25 },
    "duration": 500
   },
   "select_button 2.aseprite": {
    "frame": { "x": 32, "y": 0, "w": 16, "h": 25 },
    "rotated": false,
    "trimmed": false,
    "spriteSourceSize": { "x": 0, "y": 0, "w": 16, "h": 25 },
    "sourceSize": { "w": 16, "h": 25 },
    "duration": 500
   },
   "select_button 3.aseprite": {
    "frame": { "x": 48, "y": 0, "w": 16, "h": 25 },
    "rotated": false,
    "trimmed": false,
    "spriteSourceSize": { "x": 0, "y": 0, "w": 16, "h": 25 },
    "sourceSize": { "w": 16, "h": 25 },
    "duration": 500
   },
   "select_button 4.aseprite": {
    "frame": { "x": 64, "y": 0, "w": 16, "h": 25 },
    "rotated": false,
    "trimmed": false,
    "spriteSourceSize": { "x": 0, "y": 0, "w": 16, "h": 25 },
    "sourceSize": { "w": 16, "h": 25 },
    "duration": 500
   },
   "select_button 5.aseprite": {
    "frame": { "x": 80, "y": 0, "w": 16, "h": 25 },
    "rotated": false,
    "trimmed": false,
    "spriteSourceSize": { "x": 0, "y": 0, "w": 16, "h": 25 },
    "sourceSize": { "w": 16, "h": 25 },
    "duration": 500
   },
   "select_button 6.aseprite": {
    "frame": { "x": 96, "y": 0, "w": 16, "h": 25 },
    "rotated": false,
    "trimmed": false,
    "spriteSourceSize": { "x": 0, "y": 0, "w": 16, "h": 25 },
    "sourceSize": { "w": 16, "h": 25 },
    "duration": 500
   },
   "select_button 7.aseprite": {
    "frame": { "x": 112, "y": 0, "w": 16, "h": 25 },
    "rotated": false,
    "trimmed": false,
    "spriteSourceSize": { "x": 0, "y": 0, "w": 16, "h": 25 },
    "sourceSize": { "w": 16, "h": 25 },
    "duration": 500
   }
 },
 "meta": {
  "app": "https://www.aseprite.org/",
  "version": "1.2.34.1-x64",
  "format": "RGBA8888",
  "size": { "w": 128, "h": 25 },
  "scale": "1",
  "frameTags": [
  ],
  "layers": [
   { "name": "Layer 1", "opacity": 255, "blendMode": "normal" }
  ],
  "slices": [
  ]
 }
}
